{
  "round": 26,
  "nodes": {
    "0": {
      "accuracy": 0.8859999775886536,
      "test_loss": 0.39064714312553406,
      "precision": 1.0,
      "recall": 0.0,
      "f1_score": 0.0,
      "update_norm": 0.0,
      "is_attacker": false,
      "eps_n": 4.333152221980979
    },
    "1": {
      "accuracy": 0.8901999592781067,
      "test_loss": 0.3788885772228241,
      "precision": 1.0,
      "recall": 0.0,
      "f1_score": 0.0,
      "update_norm": 0.0,
      "is_attacker": false,
      "eps_n": 3.6539306926578625
    },
    "2": {
      "accuracy": 0.8054999709129333,
      "test_loss": 0.660872757434845,
      "precision": 1.0,
      "recall": 0.0,
      "f1_score": 0.0,
      "update_norm": 0.0,
      "is_attacker": false,
      "eps_n": 4.245287368378164
    },
    "3": {
      "accuracy": 0.8319999575614929,
      "test_loss": 0.5911768674850464,
      "precision": 1.0,
      "recall": 0.0,
      "f1_score": 0.0,
      "update_norm": 0.0,
      "is_attacker": false,
      "eps_n": 4.44520195722272
    },
    "4": {
      "accuracy": 0.8912000060081482,
      "test_loss": 0.3805990517139435,
      "precision": 1.0,
      "recall": 0.0,
      "f1_score": 0.0,
      "update_norm": 0.0,
      "is_attacker": false,
      "eps_n": 3.682187843693818
    },
    "5": {
      "accuracy": 0.8923999667167664,
      "test_loss": 0.37557825446128845,
      "precision": 1.0,
      "recall": 0.0,
      "f1_score": 0.0,
      "update_norm": 0.0,
      "is_attacker": false,
      "eps_n": 3.506676989433844
    },
    "6": {
      "accuracy": 0.8529999852180481,
      "test_loss": 0.4821021258831024,
      "precision": 1.0,
      "recall": 0.0,
      "f1_score": 0.0,
      "update_norm": 0.0,
      "is_attacker": false,
      "eps_n": 5.063542892292154
    },
    "7": {
      "accuracy": 0.776199996471405,
      "test_loss": 0.7910574078559875,
      "precision": 1.0,
      "recall": 0.0,
      "f1_score": 0.0,
      "update_norm": 0.0,
      "is_attacker": false,
      "eps_n": 5.279657816361785
    },
    "8": {
      "accuracy": 0.8258999586105347,
      "test_loss": 0.5953962206840515,
      "precision": 1.0,
      "recall": 0.0,
      "f1_score": 0.0,
      "update_norm": 0.0,
      "is_attacker": false,
      "eps_n": 4.579390585846204
    },
    "9": {
      "accuracy": 0.8215999603271484,
      "test_loss": 0.5408437252044678,
      "precision": 0.0,
      "recall": 0.0,
      "f1_score": 0.0,
      "update_norm": 5.468073844909668,
      "is_attacker": false,
      "krum_score": 320.3265380859375,
      "trust": 0.854163408279419,
      "noise_norm": 119.87787628173828,
      "n_dp_norm": 119.87787628173828,
      "nsr": 2486.4425527183957,
      "sigma_dp": 0.7514184252398585,
      "sigma_n": 0.7514184252398585,
      "eps_n": 6.024586847984072
    },
    "10": {
      "accuracy": 0.8890999555587769,
      "test_loss": 0.3771182596683502,
      "precision": 1.0,
      "recall": 0.0,
      "f1_score": 0.0,
      "update_norm": 0.0,
      "is_attacker": false,
      "eps_n": 3.699447578509751
    },
    "11": {
      "accuracy": 0.8775999546051025,
      "test_loss": 0.4086252450942993,
      "precision": 1.0,
      "recall": 0.0,
      "f1_score": 0.0,
      "update_norm": 0.0,
      "is_attacker": false,
      "eps_n": 2.6692767560644524
    },
    "12": {
      "accuracy": 0.7471999526023865,
      "test_loss": 0.7649844288825989,
      "precision": 0.0,
      "recall": 0.0,
      "f1_score": 0.0,
      "update_norm": 5.851008415222168,
      "is_attacker": false,
      "krum_score": 320.3265380859375,
      "trust": 0.8323465585708618,
      "noise_norm": 121.71237182617188,
      "n_dp_norm": 121.71237182617188,
      "nsr": 1912.0494792932993,
      "sigma_dp": 0.7657255114074263,
      "sigma_n": 0.7657255114074263,
      "eps_n": 6.133079922322997
    },
    "13": {
      "accuracy": 0.8442999720573425,
      "test_loss": 0.5033188462257385,
      "precision": 1.0,
      "recall": 0.0,
      "f1_score": 0.0,
      "update_norm": 0.0,
      "is_attacker": false,
      "eps_n": 5.395270416523764
    },
    "14": {
      "accuracy": 0.8951999545097351,
      "test_loss": 0.362330824136734,
      "precision": 1.0,
      "recall": 0.0,
      "f1_score": 0.0,
      "update_norm": 0.0,
      "is_attacker": false,
      "eps_n": 0.0
    },
    "15": {
      "accuracy": 0.8743000030517578,
      "test_loss": 0.41792210936546326,
      "precision": 0.0,
      "recall": 0.0,
      "f1_score": 0.0,
      "update_norm": 1.6852136850357056,
      "is_attacker": false,
      "krum_score": 320.3265380859375,
      "trust": 0.42916324734687805,
      "noise_norm": 164.4421844482422,
      "n_dp_norm": 164.4421844482422,
      "nsr": 2044.367826295926,
      "sigma_dp": 1.0301256632196456,
      "sigma_n": 1.0301256632196456,
      "eps_n": 5.80709844853592
    },
    "16": {
      "accuracy": 0.8895999789237976,
      "test_loss": 0.37992602586746216,
      "precision": 1.0,
      "recall": 0.0,
      "f1_score": 0.0,
      "update_norm": 0.0,
      "is_attacker": false,
      "eps_n": 2.890490096835184
    },
    "17": {
      "accuracy": 0.8702999949455261,
      "test_loss": 0.41957971453666687,
      "precision": 1.0,
      "recall": 0.0,
      "f1_score": 0.0,
      "update_norm": 0.0,
      "is_attacker": false,
      "eps_n": 3.3157325378906686
    },
    "18": {
      "accuracy": 0.7123000025749207,
      "test_loss": 1.7236193418502808,
      "precision": 1.0,
      "recall": 0.0,
      "f1_score": 0.0,
      "update_norm": 0.0,
      "is_attacker": false,
      "eps_n": 5.573162850669265
    },
    "19": {
      "accuracy": 0.7325999736785889,
      "test_loss": 1.2447307109832764,
      "precision": 1.0,
      "recall": 0.0,
      "f1_score": 0.0,
      "update_norm": 0.0,
      "is_attacker": false,
      "eps_n": 5.184455544418104
    },
    "20": {
      "accuracy": 0.7849999666213989,
      "test_loss": 0.8578583002090454,
      "precision": 1.0,
      "recall": 0.0,
      "f1_score": 0.0,
      "update_norm": 0.0,
      "is_attacker": false,
      "eps_n": 4.293178217626044
    },
    "21": {
      "accuracy": 0.8969999551773071,
      "test_loss": 0.36824092268943787,
      "precision": 1.0,
      "recall": 0.0,
      "f1_score": 0.0,
      "update_norm": 0.0,
      "is_attacker": false,
      "eps_n": 3.112611879653195
    },
    "22": {
      "accuracy": 0.8914999961853027,
      "test_loss": 0.37596645951271057,
      "precision": 1.0,
      "recall": 0.0,
      "f1_score": 0.0,
      "update_norm": 0.0,
      "is_attacker": false,
      "eps_n": 4.562257954443956
    },
    "23": {
      "accuracy": 0.8892999887466431,
      "test_loss": 0.3812374770641327,
      "precision": 1.0,
      "recall": 0.0,
      "f1_score": 0.0,
      "update_norm": 0.0,
      "is_attacker": false,
      "eps_n": 3.3751395132832887
    },
    "24": {
      "accuracy": 0.8873999714851379,
      "test_loss": 0.38967397809028625,
      "precision": 0.0,
      "recall": 0.0,
      "f1_score": 0.0,
      "update_norm": 2.5825576782226562,
      "is_attacker": false,
      "krum_score": 355.9773254394531,
      "trust": 0.8767956495285034,
      "noise_norm": 117.26556396484375,
      "n_dp_norm": 117.26556396484375,
      "nsr": 2328.6388657394823,
      "sigma_dp": 0.736576620394458,
      "sigma_n": 0.736576620394458,
      "eps_n": 6.296312771903794
    },
    "25": {
      "accuracy": 0.8955000042915344,
      "test_loss": 0.37343621253967285,
      "precision": 1.0,
      "recall": 0.0,
      "f1_score": 0.0,
      "update_norm": 0.0,
      "is_attacker": false,
      "eps_n": 2.8195636533734056
    },
    "26": {
      "accuracy": 0.8931999802589417,
      "test_loss": 0.3720106780529022,
      "precision": 1.0,
      "recall": 0.0,
      "f1_score": 0.0,
      "update_norm": 0.0,
      "is_attacker": false,
      "eps_n": 2.6195304049508525
    },
    "27": {
      "accuracy": 0.8913999795913696,
      "test_loss": 0.3708581328392029,
      "precision": 1.0,
      "recall": 0.0,
      "f1_score": 0.0,
      "update_norm": 0.0,
      "is_attacker": false,
      "eps_n": 4.142372036780985
    },
    "28": {
      "accuracy": 0.8458999991416931,
      "test_loss": 0.5088114738464355,
      "precision": 1.0,
      "recall": 0.0,
      "f1_score": 0.0,
      "update_norm": 0.0,
      "is_attacker": false,
      "eps_n": 3.751557163006342
    },
    "29": {
      "accuracy": 0.7893999814987183,
      "test_loss": 0.6557782292366028,
      "precision": 0.0,
      "recall": 0.0,
      "f1_score": 0.0,
      "update_norm": 4.970432758331299,
      "is_attacker": false,
      "krum_score": 358.1734924316406,
      "trust": 0.7762268781661987,
      "noise_norm": 127.87157440185547,
      "n_dp_norm": 127.87157440185547,
      "nsr": 2251.5003524248564,
      "sigma_dp": 0.802527758934986,
      "sigma_n": 0.802527758934986,
      "eps_n": 5.878950516510897
    },
    "30": {
      "accuracy": 0.8206999897956848,
      "test_loss": 0.5731320381164551,
      "precision": 1.0,
      "recall": 0.0,
      "f1_score": 0.0,
      "update_norm": 0.0,
      "is_attacker": false,
      "eps_n": 5.961907809214556
    },
    "31": {
      "accuracy": 0.8888999819755554,
      "test_loss": 0.3856455385684967,
      "precision": 1.0,
      "recall": 0.0,
      "f1_score": 0.0,
      "update_norm": 0.0,
      "is_attacker": false,
      "eps_n": 3.5485370383011134
    },
    "32": {
      "accuracy": 0.8400999903678894,
      "test_loss": 0.5125818252563477,
      "precision": 1.0,
      "recall": 0.0,
      "f1_score": 0.0,
      "update_norm": 0.0,
      "is_attacker": false,
      "eps_n": 4.636696168912379
    },
    "33": {
      "accuracy": 0.8947999477386475,
      "test_loss": 0.36690741777420044,
      "precision": 1.0,
      "recall": 0.0,
      "f1_score": 0.0,
      "update_norm": 0.0,
      "is_attacker": false,
      "eps_n": 3.825013638073031
    },
    "34": {
      "accuracy": 0.8361999988555908,
      "test_loss": 0.5252177715301514,
      "precision": 1.0,
      "recall": 0.0,
      "f1_score": 0.0,
      "update_norm": 0.0,
      "is_attacker": false,
      "eps_n": 3.6433930978565328
    },
    "35": {
      "accuracy": 0.875,
      "test_loss": 0.423005610704422,
      "precision": 1.0,
      "recall": 0.0,
      "f1_score": 0.0,
      "update_norm": 0.0,
      "is_attacker": false,
      "eps_n": 4.104276307446416
    },
    "36": {
      "accuracy": 0.8924999833106995,
      "test_loss": 0.3681296706199646,
      "precision": 1.0,
      "recall": 0.0,
      "f1_score": 0.0,
      "update_norm": 0.0,
      "is_attacker": false,
      "eps_n": 2.744531748257917
    },
    "37": {
      "accuracy": 0.8886999487876892,
      "test_loss": 0.3829139769077301,
      "precision": 1.0,
      "recall": 0.0,
      "f1_score": 0.0,
      "update_norm": 0.0,
      "is_attacker": false,
      "eps_n": 2.9088034531457785
    },
    "38": {
      "accuracy": 0.7744999527931213,
      "test_loss": 0.8047484159469604,
      "precision": 1.0,
      "recall": 0.0,
      "f1_score": 0.0,
      "update_norm": 0.0,
      "is_attacker": false,
      "eps_n": 5.231430461322881
    },
    "39": {
      "accuracy": 0.7687999606132507,
      "test_loss": 0.9179608225822449,
      "precision": 1.0,
      "recall": 0.0,
      "f1_score": 0.0,
      "update_norm": 0.0,
      "is_attacker": false,
      "eps_n": 5.090978613794115
    },
    "40": {
      "accuracy": 0.8758999705314636,
      "test_loss": 0.4265817403793335,
      "precision": 1.0,
      "recall": 0.0,
      "f1_score": 0.0,
      "update_norm": 0.0,
      "is_attacker": false,
      "eps_n": 4.410782562197985
    },
    "41": {
      "accuracy": 0.8969999551773071,
      "test_loss": 0.36186328530311584,
      "precision": 1.0,
      "recall": 0.0,
      "f1_score": 0.0,
      "update_norm": 0.0,
      "is_attacker": false,
      "eps_n": 0.0
    },
    "42": {
      "accuracy": 0.8276000022888184,
      "test_loss": 0.5499086976051331,
      "precision": 1.0,
      "recall": 0.0,
      "f1_score": 0.0,
      "update_norm": 0.0,
      "is_attacker": false,
      "eps_n": 3.577730330378152
    },
    "43": {
      "accuracy": 0.8919000029563904,
      "test_loss": 0.37378135323524475,
      "precision": 1.0,
      "recall": 0.0,
      "f1_score": 0.0,
      "update_norm": 0.0,
      "is_attacker": false,
      "eps_n": 2.5696906453486514
    },
    "44": {
      "accuracy": 0.8964999914169312,
      "test_loss": 0.3648311197757721,
      "precision": 1.0,
      "recall": 0.0,
      "f1_score": 0.0,
      "update_norm": 0.0,
      "is_attacker": false,
      "eps_n": 4.331732333103867
    },
    "45": {
      "accuracy": 0.8947999477386475,
      "test_loss": 0.37148427963256836,
      "precision": 1.0,
      "recall": 0.0,
      "f1_score": 0.0,
      "update_norm": 0.0,
      "is_attacker": false,
      "eps_n": 0.0
    },
    "46": {
      "accuracy": 0.887499988079071,
      "test_loss": 0.3748806416988373,
      "precision": 1.0,
      "recall": 0.0,
      "f1_score": 0.0,
      "update_norm": 0.0,
      "is_attacker": false,
      "eps_n": 2.5998582399100125
    },
    "47": {
      "accuracy": 0.8361999988555908,
      "test_loss": 0.5267212986946106,
      "precision": 1.0,
      "recall": 0.0,
      "f1_score": 0.0,
      "update_norm": 0.0,
      "is_attacker": false,
      "eps_n": 4.980253791315776
    },
    "48": {
      "accuracy": 0.8830999732017517,
      "test_loss": 0.38324660062789917,
      "precision": 1.0,
      "recall": 0.0,
      "f1_score": 0.0,
      "update_norm": 0.0,
      "is_attacker": false,
      "eps_n": 3.4754163605234236
    },
    "49": {
      "accuracy": 0.8883999586105347,
      "test_loss": 0.3846966326236725,
      "precision": 1.0,
      "recall": 0.0,
      "f1_score": 0.0,
      "update_norm": 0.0,
      "is_attacker": false,
      "eps_n": 5.745519862855406
    },
    "50": {
      "accuracy": 0.892799973487854,
      "test_loss": 0.3725701868534088,
      "precision": 1.0,
      "recall": 0.0,
      "f1_score": 0.0,
      "update_norm": 0.0,
      "is_attacker": false,
      "eps_n": 2.992527367108644
    },
    "51": {
      "accuracy": 0.8868999481201172,
      "test_loss": 0.3837544322013855,
      "precision": 1.0,
      "recall": 0.0,
      "f1_score": 0.0,
      "update_norm": 0.0,
      "is_attacker": false,
      "eps_n": 2.6244446095874254
    },
    "52": {
      "accuracy": 0.8763999938964844,
      "test_loss": 0.4095572233200073,
      "precision": 1.0,
      "recall": 0.0,
      "f1_score": 0.0,
      "update_norm": 0.0,
      "is_attacker": false,
      "eps_n": 4.493698409488673
    },
    "53": {
      "accuracy": 0.8578000068664551,
      "test_loss": 0.46703776717185974,
      "precision": 1.0,
      "recall": 0.0,
      "f1_score": 0.0,
      "update_norm": 0.0,
      "is_attacker": false,
      "eps_n": 5.525426652223235
    },
    "54": {
      "accuracy": 0.8330999612808228,
      "test_loss": 0.5474053621292114,
      "precision": 1.0,
      "recall": 0.0,
      "f1_score": 0.0,
      "update_norm": 0.0,
      "is_attacker": false,
      "eps_n": 4.732669568277443
    },
    "55": {
      "accuracy": 0.8913999795913696,
      "test_loss": 0.37972408533096313,
      "precision": 1.0,
      "recall": 0.0,
      "f1_score": 0.0,
      "update_norm": 0.0,
      "is_attacker": false,
      "eps_n": 0.0
    },
    "56": {
      "accuracy": 0.8940999507904053,
      "test_loss": 0.3776608407497406,
      "precision": 1.0,
      "recall": 0.0,
      "f1_score": 0.0,
      "update_norm": 0.0,
      "is_attacker": false,
      "eps_n": 3.825013638073031
    },
    "57": {
      "accuracy": 0.8644999861717224,
      "test_loss": 0.44446951150894165,
      "precision": 1.0,
      "recall": 0.0,
      "f1_score": 0.0,
      "update_norm": 0.0,
      "is_attacker": false,
      "eps_n": 3.345073049776566
    },
    "58": {
      "accuracy": 0.8964999914169312,
      "test_loss": 0.36359283328056335,
      "precision": 1.0,
      "recall": 0.0,
      "f1_score": 0.0,
      "update_norm": 0.0,
      "is_attacker": false,
      "eps_n": 2.6778933337224764
    },
    "59": {
      "accuracy": 0.8995999693870544,
      "test_loss": 0.36085543036460876,
      "precision": 1.0,
      "recall": 0.0,
      "f1_score": 0.0,
      "update_norm": 0.0,
      "is_attacker": false,
      "eps_n": 0.0
    },
    "60": {
      "accuracy": 0.66839998960495,
      "test_loss": 1.269405484199524,
      "precision": 0.0,
      "recall": 0.0,
      "f1_score": 0.0,
      "update_norm": 8.30515193939209,
      "is_attacker": false,
      "krum_score": 251.15969848632812,
      "trust": 0.859449028968811,
      "noise_norm": 119.58676147460938,
      "n_dp_norm": 119.58676147460938,
      "nsr": 1699.1551920672043,
      "sigma_dp": 0.747952213038628,
      "sigma_n": 0.747952213038628,
      "eps_n": 6.190548935880066
    },
    "61": {
      "accuracy": 0.8700000047683716,
      "test_loss": 0.42815741896629333,
      "precision": 1.0,
      "recall": 0.0,
      "f1_score": 0.0,
      "update_norm": 0.0,
      "is_attacker": false,
      "eps_n": 4.490343256319988
    },
    "62": {
      "accuracy": 0.892799973487854,
      "test_loss": 0.3780365586280823,
      "precision": 1.0,
      "recall": 0.0,
      "f1_score": 0.0,
      "update_norm": 0.0,
      "is_attacker": false,
      "eps_n": 4.8422348749350235
    },
    "63": {
      "accuracy": 0.892799973487854,
      "test_loss": 0.3751095235347748,
      "precision": 1.0,
      "recall": 0.0,
      "f1_score": 0.0,
      "update_norm": 0.0,
      "is_attacker": false,
      "eps_n": 2.744531748257917
    },
    "64": {
      "accuracy": 0.8866999745368958,
      "test_loss": 0.3848419189453125,
      "precision": 1.0,
      "recall": 0.0,
      "f1_score": 0.0,
      "update_norm": 0.0,
      "is_attacker": false,
      "eps_n": 2.79141813577445
    },
    "65": {
      "accuracy": 0.8931999802589417,
      "test_loss": 0.36853674054145813,
      "precision": 1.0,
      "recall": 0.0,
      "f1_score": 0.0,
      "update_norm": 0.0,
      "is_attacker": false,
      "eps_n": 3.506676989433844
    },
    "66": {
      "accuracy": 0.8849999904632568,
      "test_loss": 0.39038410782814026,
      "precision": 1.0,
      "recall": 0.0,
      "f1_score": 0.0,
      "update_norm": 0.0,
      "is_attacker": false,
      "eps_n": 2.651632338839052
    },
    "67": {
      "accuracy": 0.6469999551773071,
      "test_loss": 1.3900783061981201,
      "precision": 1.0,
      "recall": 0.0,
      "f1_score": 0.0,
      "update_norm": 0.0,
      "is_attacker": false,
      "eps_n": 6.109666638838713
    },
    "68": {
      "accuracy": 0.7851999998092651,
      "test_loss": 0.7787967324256897,
      "precision": 1.0,
      "recall": 0.0,
      "f1_score": 0.0,
      "update_norm": 0.0,
      "is_attacker": false,
      "eps_n": 4.393992436092314
    },
    "69": {
      "accuracy": 0.8917999863624573,
      "test_loss": 0.3746758997440338,
      "precision": 1.0,
      "recall": 0.0,
      "f1_score": 0.0,
      "update_norm": 0.0,
      "is_attacker": false,
      "eps_n": 2.8195636533734056
    },
    "70": {
      "accuracy": 0.8514999747276306,
      "test_loss": 0.49498215317726135,
      "precision": 1.0,
      "recall": 0.0,
      "f1_score": 0.0,
      "update_norm": 0.0,
      "is_attacker": false,
      "eps_n": 4.152770492206546
    },
    "71": {
      "accuracy": 0.8881999850273132,
      "test_loss": 0.38413119316101074,
      "precision": 1.0,
      "recall": 0.0,
      "f1_score": 0.0,
      "update_norm": 0.0,
      "is_attacker": false,
      "eps_n": 2.7065070247251923
    },
    "72": {
      "accuracy": 0.8863999843597412,
      "test_loss": 0.3832206130027771,
      "precision": 1.0,
      "recall": 0.0,
      "f1_score": 0.0,
      "update_norm": 0.0,
      "is_attacker": false,
      "eps_n": 2.744531748257917
    },
    "73": {
      "accuracy": 0.8517999649047852,
      "test_loss": 0.5007213950157166,
      "precision": 1.0,
      "recall": 0.0,
      "f1_score": 0.0,
      "update_norm": 0.0,
      "is_attacker": false,
      "eps_n": 4.285039677657391
    },
    "74": {
      "accuracy": 0.8465999960899353,
      "test_loss": 0.500693142414093,
      "precision": 1.0,
      "recall": 0.0,
      "f1_score": 0.0,
      "update_norm": 0.0,
      "is_attacker": false,
      "eps_n": 4.4242434846520045
    },
    "75": {
      "accuracy": 0.7770000100135803,
      "test_loss": 0.8214344382286072,
      "precision": 1.0,
      "recall": 0.0,
      "f1_score": 0.0,
      "update_norm": 0.0,
      "is_attacker": false,
      "eps_n": 5.541479675732359
    },
    "76": {
      "accuracy": 0.8877999782562256,
      "test_loss": 0.38067781925201416,
      "precision": 1.0,
      "recall": 0.0,
      "f1_score": 0.0,
      "update_norm": 0.0,
      "is_attacker": false,
      "eps_n": 3.0897337188762317
    },
    "77": {
      "accuracy": 0.8603999614715576,
      "test_loss": 0.460103303194046,
      "precision": 1.0,
      "recall": 0.0,
      "f1_score": 0.0,
      "update_norm": 0.0,
      "is_attacker": false,
      "eps_n": 3.9316315214612088
    },
    "78": {
      "accuracy": 0.8962000012397766,
      "test_loss": 0.36299100518226624,
      "precision": 1.0,
      "recall": 0.0,
      "f1_score": 0.0,
      "update_norm": 0.0,
      "is_attacker": false,
      "eps_n": 2.444367403079083
    },
    "79": {
      "accuracy": 0.8925999999046326,
      "test_loss": 0.3787461221218109,
      "precision": 1.0,
      "recall": 0.0,
      "f1_score": 0.0,
      "update_norm": 0.0,
      "is_attacker": false,
      "eps_n": 2.3686261975277554
    },
    "80": {
      "accuracy": 0.8082000017166138,
      "test_loss": 0.6592370271682739,
      "precision": 1.0,
      "recall": 0.0,
      "f1_score": 0.0,
      "update_norm": 0.0,
      "is_attacker": false,
      "eps_n": 4.122381392687688
    },
    "81": {
      "accuracy": 0.8896999955177307,
      "test_loss": 0.37298551201820374,
      "precision": 1.0,
      "recall": 0.0,
      "f1_score": 0.0,
      "update_norm": 0.0,
      "is_attacker": false,
      "eps_n": 4.8774543395724175
    },
    "82": {
      "accuracy": 0.8950999975204468,
      "test_loss": 0.3655405342578888,
      "precision": 1.0,
      "recall": 0.0,
      "f1_score": 0.0,
      "update_norm": 0.0,
      "is_attacker": false,
      "eps_n": 3.506676989433844
    },
    "83": {
      "accuracy": 0.8661999702453613,
      "test_loss": 0.4491799771785736,
      "precision": 1.0,
      "recall": 0.0,
      "f1_score": 0.0,
      "update_norm": 0.0,
      "is_attacker": false,
      "eps_n": 5.144122402685138
    },
    "84": {
      "accuracy": 0.8585999608039856,
      "test_loss": 0.459155797958374,
      "precision": 1.0,
      "recall": 0.0,
      "f1_score": 0.0,
      "update_norm": 0.0,
      "is_attacker": false,
      "eps_n": 2.97922567255415
    },
    "85": {
      "accuracy": 0.8357999920845032,
      "test_loss": 0.514427661895752,
      "precision": 1.0,
      "recall": 0.0,
      "f1_score": 0.0,
      "update_norm": 0.0,
      "is_attacker": false,
      "eps_n": 4.114251550186634
    },
    "86": {
      "accuracy": 0.8380999565124512,
      "test_loss": 0.5227735638618469,
      "precision": 1.0,
      "recall": 0.0,
      "f1_score": 0.0,
      "update_norm": 0.0,
      "is_attacker": false,
      "eps_n": 4.494181738067709
    },
    "87": {
      "accuracy": 0.8966999650001526,
      "test_loss": 0.3674008548259735,
      "precision": 1.0,
      "recall": 0.0,
      "f1_score": 0.0,
      "update_norm": 0.0,
      "is_attacker": false,
      "eps_n": 5.165456067490475
    },
    "88": {
      "accuracy": 0.896399974822998,
      "test_loss": 0.3685343265533447,
      "precision": 1.0,
      "recall": 0.0,
      "f1_score": 0.0,
      "update_norm": 0.0,
      "is_attacker": false,
      "eps_n": 6.345043387219871
    },
    "89": {
      "accuracy": 0.8901000022888184,
      "test_loss": 0.3734195828437805,
      "precision": 1.0,
      "recall": 0.0,
      "f1_score": 0.0,
      "update_norm": 0.0,
      "is_attacker": false,
      "eps_n": 6.345043387219871
    },
    "90": {
      "accuracy": 0.8445999622344971,
      "test_loss": 0.4918076992034912,
      "precision": 1.0,
      "recall": 0.0,
      "f1_score": 0.0,
      "update_norm": 0.0,
      "is_attacker": false,
      "eps_n": 4.826000544473053
    },
    "91": {
      "accuracy": 0.886199951171875,
      "test_loss": 0.38568824529647827,
      "precision": 1.0,
      "recall": 0.0,
      "f1_score": 0.0,
      "update_norm": 0.0,
      "is_attacker": false,
      "eps_n": 3.560252202677474
    },
    "92": {
      "accuracy": 0.7432999610900879,
      "test_loss": 0.9460921883583069,
      "precision": 1.0,
      "recall": 0.0,
      "f1_score": 0.0,
      "update_norm": 0.0,
      "is_attacker": false,
      "eps_n": 5.836522108400192
    },
    "93": {
      "accuracy": 0.8876999616622925,
      "test_loss": 0.3848543167114258,
      "precision": 1.0,
      "recall": 0.0,
      "f1_score": 0.0,
      "update_norm": 0.0,
      "is_attacker": false,
      "eps_n": 3.5407071431885084
    },
    "94": {
      "accuracy": 0.8970999717712402,
      "test_loss": 0.3648126721382141,
      "precision": 1.0,
      "recall": 0.0,
      "f1_score": 0.0,
      "update_norm": 0.0,
      "is_attacker": false,
      "eps_n": 0.0
    },
    "95": {
      "accuracy": 0.8840999603271484,
      "test_loss": 0.38712871074676514,
      "precision": 1.0,
      "recall": 0.0,
      "f1_score": 0.0,
      "update_norm": 0.0,
      "is_attacker": false,
      "eps_n": 3.573414880770417
    },
    "96": {
      "accuracy": 0.887999951839447,
      "test_loss": 0.38173583149909973,
      "precision": 1.0,
      "recall": 0.0,
      "f1_score": 0.0,
      "update_norm": 0.0,
      "is_attacker": false,
      "eps_n": 3.728572428873819
    },
    "97": {
      "accuracy": 0.6862999796867371,
      "test_loss": 1.0650489330291748,
      "precision": 0.0,
      "recall": 0.0,
      "f1_score": 0.0,
      "update_norm": 5.872536659240723,
      "is_attacker": false,
      "krum_score": 209.70401000976562,
      "trust": 0.6836881041526794,
      "noise_norm": 137.7219696044922,
      "n_dp_norm": 137.7219696044922,
      "nsr": 801.2317891415125,
      "sigma_dp": 0.863212973864675,
      "sigma_n": 0.863212973864675,
      "eps_n": 6.230048072966208
    },
    "98": {
      "accuracy": 0.892799973487854,
      "test_loss": 0.3705831468105316,
      "precision": 1.0,
      "recall": 0.0,
      "f1_score": 0.0,
      "update_norm": 0.0,
      "is_attacker": false,
      "eps_n": 3.2644354503319137
    },
    "99": {
      "accuracy": 0.8854999542236328,
      "test_loss": 0.3967048227787018,
      "precision": 1.0,
      "recall": 0.0,
      "f1_score": 0.0,
      "update_norm": 0.0,
      "is_attacker": false,
      "eps_n": 4.27182296292944
    },
    "100": {
      "accuracy": 0.8941999673843384,
      "test_loss": 0.3699490427970886,
      "precision": 0.0,
      "recall": 0.0,
      "f1_score": 0.0,
      "update_norm": 1.047182559967041,
      "is_attacker": false,
      "krum_score": 201.91033935546875,
      "trust": 1.0,
      "noise_norm": 104.71796417236328,
      "n_dp_norm": 104.71796417236328,
      "nsr": 2150.421934095282,
      "sigma_dp": 0.6557814881016614,
      "sigma_n": 0.6557814881016614,
      "eps_n": 6.920827264404566
    },
    "101": {
      "accuracy": 0.7938999533653259,
      "test_loss": 0.6636452674865723,
      "precision": 1.0,
      "recall": 0.0,
      "f1_score": 0.0,
      "update_norm": 0.0,
      "is_attacker": false,
      "eps_n": 5.551760354501445
    },
    "102": {
      "accuracy": 0.8197999596595764,
      "test_loss": 0.5800955891609192,
      "precision": 1.0,
      "recall": 0.0,
      "f1_score": 0.0,
      "update_norm": 0.0,
      "is_attacker": false,
      "eps_n": 3.7245402035758053
    },
    "103": {
      "accuracy": 0.8290999531745911,
      "test_loss": 0.5747724175453186,
      "precision": 1.0,
      "recall": 0.0,
      "f1_score": 0.0,
      "update_norm": 0.0,
      "is_attacker": false,
      "eps_n": 3.405048841683154
    },
    "104": {
      "accuracy": 0.8908999562263489,
      "test_loss": 0.3710249662399292,
      "precision": 1.0,
      "recall": 0.0,
      "f1_score": 0.0,
      "update_norm": 0.0,
      "is_attacker": false,
      "eps_n": 2.87550177601441
    },
    "105": {
      "accuracy": 0.87909996509552,
      "test_loss": 0.41365981101989746,
      "precision": 1.0,
      "recall": 0.0,
      "f1_score": 0.0,
      "update_norm": 0.0,
      "is_attacker": false,
      "eps_n": 3.615731921403225
    },
    "106": {
      "accuracy": 0.7882999777793884,
      "test_loss": 0.6700939536094666,
      "precision": 0.0,
      "recall": 0.0,
      "f1_score": 0.0,
      "update_norm": 5.371392250061035,
      "is_attacker": false,
      "krum_score": 176.08590698242188,
      "trust": 0.6765036582946777,
      "noise_norm": 139.0962371826172,
      "n_dp_norm": 139.0962371826172,
      "nsr": 1892.510704279643,
      "sigma_dp": 0.8679244004606211,
      "sigma_n": 0.8679244004606211,
      "eps_n": 5.746038023128661
    },
    "107": {
      "accuracy": 0.8618999719619751,
      "test_loss": 0.45788317918777466,
      "precision": 1.0,
      "recall": 0.0,
      "f1_score": 0.0,
      "update_norm": 0.0,
      "is_attacker": false,
      "eps_n": 3.5482658143914083
    },
    "108": {
      "accuracy": 0.8714999556541443,
      "test_loss": 0.42523303627967834,
      "precision": 1.0,
      "recall": 0.0,
      "f1_score": 0.0,
      "update_norm": 0.0,
      "is_attacker": false,
      "eps_n": 3.667142159145047
    },
    "109": {
      "accuracy": 0.5817999839782715,
      "test_loss": 2.2277960777282715,
      "precision": 1.0,
      "recall": 0.0,
      "f1_score": 0.0,
      "update_norm": 0.0,
      "is_attacker": false,
      "eps_n": 6.880735911839236
    },
    "110": {
      "accuracy": 0.8657000064849854,
      "test_loss": 0.4413782060146332,
      "precision": 1.0,
      "recall": 0.0,
      "f1_score": 0.0,
      "update_norm": 0.0,
      "is_attacker": false,
      "eps_n": 5.489214783247772
    },
    "111": {
      "accuracy": 0.8858000040054321,
      "test_loss": 0.39359912276268005,
      "precision": 1.0,
      "recall": 0.0,
      "f1_score": 0.0,
      "update_norm": 0.0,
      "is_attacker": false,
      "eps_n": 3.6634887920820844
    },
    "112": {
      "accuracy": 0.8952999711036682,
      "test_loss": 0.3643311858177185,
      "precision": 1.0,
      "recall": 0.0,
      "f1_score": 0.0,
      "update_norm": 0.0,
      "is_attacker": false,
      "eps_n": 0.0
    },
    "113": {
      "accuracy": 0.8666999936103821,
      "test_loss": 0.4404134154319763,
      "precision": 1.0,
      "recall": 0.0,
      "f1_score": 0.0,
      "update_norm": 0.0,
      "is_attacker": false,
      "eps_n": 5.082340734398667
    },
    "114": {
      "accuracy": 0.8953999876976013,
      "test_loss": 0.37004369497299194,
      "precision": 1.0,
      "recall": 0.0,
      "f1_score": 0.0,
      "update_norm": 0.0,
      "is_attacker": false,
      "eps_n": 4.142372036780985
    },
    "115": {
      "accuracy": 0.8920999765396118,
      "test_loss": 0.38077232241630554,
      "precision": 1.0,
      "recall": 0.0,
      "f1_score": 0.0,
      "update_norm": 0.0,
      "is_attacker": false,
      "eps_n": 0.0
    },
    "116": {
      "accuracy": 0.8851999640464783,
      "test_loss": 0.3852771818637848,
      "precision": 1.0,
      "recall": 0.0,
      "f1_score": 0.0,
      "update_norm": 0.0,
      "is_attacker": false,
      "eps_n": 3.4211146875159075
    },
    "117": {
      "accuracy": 0.8895999789237976,
      "test_loss": 0.36954939365386963,
      "precision": 1.0,
      "recall": 0.0,
      "f1_score": 0.0,
      "update_norm": 0.0,
      "is_attacker": false,
      "eps_n": 5.55074993124014
    },
    "118": {
      "accuracy": 0.8937000036239624,
      "test_loss": 0.36883050203323364,
      "precision": 1.0,
      "recall": 0.0,
      "f1_score": 0.0,
      "update_norm": 0.0,
      "is_attacker": false,
      "eps_n": 3.7053997925906774
    },
    "119": {
      "accuracy": 0.8917999863624573,
      "test_loss": 0.3773530125617981,
      "precision": 1.0,
      "recall": 0.0,
      "f1_score": 0.0,
      "update_norm": 0.0,
      "is_attacker": false,
      "eps_n": 4.378097266260302
    },
    "120": {
      "accuracy": 0.8916999697685242,
      "test_loss": 0.3767920434474945,
      "precision": 1.0,
      "recall": 0.0,
      "f1_score": 0.0,
      "update_norm": 0.0,
      "is_attacker": false,
      "eps_n": 2.5696906453486514
    },
    "121": {
      "accuracy": 0.8671999573707581,
      "test_loss": 0.42850935459136963,
      "precision": 1.0,
      "recall": 0.0,
      "f1_score": 0.0,
      "update_norm": 0.0,
      "is_attacker": false,
      "eps_n": 3.749358233553263
    },
    "122": {
      "accuracy": 0.854699969291687,
      "test_loss": 0.4879581332206726,
      "precision": 1.0,
      "recall": 0.0,
      "f1_score": 0.0,
      "update_norm": 0.0,
      "is_attacker": false,
      "eps_n": 3.9357053480225686
    },
    "123": {
      "accuracy": 0.889799952507019,
      "test_loss": 0.37834474444389343,
      "precision": 1.0,
      "recall": 0.0,
      "f1_score": 0.0,
      "update_norm": 0.0,
      "is_attacker": false,
      "eps_n": 4.8422348749350235
    },
    "124": {
      "accuracy": 0.8962000012397766,
      "test_loss": 0.37002140283584595,
      "precision": 1.0,
      "recall": 0.0,
      "f1_score": 0.0,
      "update_norm": 0.0,
      "is_attacker": false,
      "eps_n": 0.0
    },
    "125": {
      "accuracy": 0.8942999839782715,
      "test_loss": 0.3706924319267273,
      "precision": 1.0,
      "recall": 0.0,
      "f1_score": 0.0,
      "update_norm": 0.0,
      "is_attacker": false,
      "eps_n": 0.0
    },
    "126": {
      "accuracy": 0.8930000066757202,
      "test_loss": 0.37107396125793457,
      "precision": 1.0,
      "recall": 0.0,
      "f1_score": 0.0,
      "update_norm": 0.0,
      "is_attacker": false,
      "eps_n": 0.0
    },
    "127": {
      "accuracy": 0.8959999680519104,
      "test_loss": 0.3697357773780823,
      "precision": 1.0,
      "recall": 0.0,
      "f1_score": 0.0,
      "update_norm": 0.0,
      "is_attacker": false,
      "eps_n": 5.510016397165074
    },
    "128": {
      "accuracy": 0.8940999507904053,
      "test_loss": 0.37004271149635315,
      "precision": 1.0,
      "recall": 0.0,
      "f1_score": 0.0,
      "update_norm": 0.0,
      "is_attacker": false,
      "eps_n": 2.8195636533734056
    },
    "129": {
      "accuracy": 0.8915999531745911,
      "test_loss": 0.3781989514827728,
      "precision": 1.0,
      "recall": 0.0,
      "f1_score": 0.0,
      "update_norm": 0.0,
      "is_attacker": false,
      "eps_n": 4.562257954443956
    },
    "130": {
      "accuracy": 0.8977999687194824,
      "test_loss": 0.36647796630859375,
      "precision": 1.0,
      "recall": 0.0,
      "f1_score": 0.0,
      "update_norm": 0.0,
      "is_attacker": false,
      "eps_n": 0.0
    },
    "131": {
      "accuracy": 0.8666999936103821,
      "test_loss": 0.44020867347717285,
      "precision": 1.0,
      "recall": 0.0,
      "f1_score": 0.0,
      "update_norm": 0.0,
      "is_attacker": false,
      "eps_n": 4.672268727304707
    },
    "132": {
      "accuracy": 0.8944000005722046,
      "test_loss": 0.3664146959781647,
      "precision": 1.0,
      "recall": 0.0,
      "f1_score": 0.0,
      "update_norm": 0.0,
      "is_attacker": false,
      "eps_n": 2.744531748257917
    },
    "133": {
      "accuracy": 0.8828999996185303,
      "test_loss": 0.39354008436203003,
      "precision": 1.0,
      "recall": 0.0,
      "f1_score": 0.0,
      "update_norm": 0.0,
      "is_attacker": false,
      "eps_n": 2.9583859779417185
    },
    "134": {
      "accuracy": 0.8951999545097351,
      "test_loss": 0.3720637857913971,
      "precision": 1.0,
      "recall": 0.0,
      "f1_score": 0.0,
      "update_norm": 0.0,
      "is_attacker": false,
      "eps_n": 4.8422348749350235
    },
    "135": {
      "accuracy": 0.8924999833106995,
      "test_loss": 0.36539870500564575,
      "precision": 1.0,
      "recall": 0.0,
      "f1_score": 0.0,
      "update_norm": 0.0,
      "is_attacker": false,
      "eps_n": 3.825013638073031
    },
    "136": {
      "accuracy": 0.8301999568939209,
      "test_loss": 0.5400716066360474,
      "precision": 1.0,
      "recall": 0.0,
      "f1_score": 0.0,
      "update_norm": 0.0,
      "is_attacker": false,
      "eps_n": 5.218176743708576
    },
    "137": {
      "accuracy": 0.8919000029563904,
      "test_loss": 0.37759628891944885,
      "precision": 1.0,
      "recall": 0.0,
      "f1_score": 0.0,
      "update_norm": 0.0,
      "is_attacker": false,
      "eps_n": 4.065718984168418
    },
    "138": {
      "accuracy": 0.8779000043869019,
      "test_loss": 0.4184753894805908,
      "precision": 1.0,
      "recall": 0.0,
      "f1_score": 0.0,
      "update_norm": 0.0,
      "is_attacker": false,
      "eps_n": 3.7339003711930445
    },
    "139": {
      "accuracy": 0.8723999857902527,
      "test_loss": 0.4277787506580353,
      "precision": 0.0,
      "recall": 0.0,
      "f1_score": 0.0,
      "update_norm": 2.261244535446167,
      "is_attacker": false,
      "krum_score": 160.39920043945312,
      "trust": 0.6255377531051636,
      "noise_norm": 144.0421142578125,
      "n_dp_norm": 144.0421142578125,
      "nsr": 1892.4954896739935,
      "sigma_dp": 0.9013468976082489,
      "sigma_n": 0.9013468976082489,
      "eps_n": 6.36321414096357
    },
    "140": {
      "accuracy": 0.8916999697685242,
      "test_loss": 0.3692633807659149,
      "precision": 1.0,
      "recall": 0.0,
      "f1_score": 0.0,
      "update_norm": 0.0,
      "is_attacker": false,
      "eps_n": 3.8115549624751965
    },
    "141": {
      "accuracy": 0.8770999908447266,
      "test_loss": 0.4226771295070648,
      "precision": 1.0,
      "recall": 0.0,
      "f1_score": 0.0,
      "update_norm": 0.0,
      "is_attacker": false,
      "eps_n": 4.123698597980656
    },
    "142": {
      "accuracy": 0.858199954032898,
      "test_loss": 0.4583268463611603,
      "precision": 1.0,
      "recall": 0.0,
      "f1_score": 0.0,
      "update_norm": 0.0,
      "is_attacker": false,
      "eps_n": 5.272805662616418
    },
    "143": {
      "accuracy": 0.8527999520301819,
      "test_loss": 0.48113250732421875,
      "precision": 1.0,
      "recall": 0.0,
      "f1_score": 0.0,
      "update_norm": 0.0,
      "is_attacker": false,
      "eps_n": 3.2621241700127577
    },
    "144": {
      "accuracy": 0.8971999883651733,
      "test_loss": 0.3716992735862732,
      "precision": 1.0,
      "recall": 0.0,
      "f1_score": 0.0,
      "update_norm": 0.0,
      "is_attacker": false,
      "eps_n": 5.9436989187151825
    },
    "145": {
      "accuracy": 0.8384999632835388,
      "test_loss": 0.518733561038971,
      "precision": 1.0,
      "recall": 0.0,
      "f1_score": 0.0,
      "update_norm": 0.0,
      "is_attacker": false,
      "eps_n": 5.0245213725036075
    },
    "146": {
      "accuracy": 0.8924999833106995,
      "test_loss": 0.3778424561023712,
      "precision": 1.0,
      "recall": 0.0,
      "f1_score": 0.0,
      "update_norm": 0.0,
      "is_attacker": false,
      "eps_n": 3.9761996984060364
    },
    "147": {
      "accuracy": 0.8903999924659729,
      "test_loss": 0.37673965096473694,
      "precision": 1.0,
      "recall": 0.0,
      "f1_score": 0.0,
      "update_norm": 0.0,
      "is_attacker": false,
      "eps_n": 5.3691225952610635
    },
    "148": {
      "accuracy": 0.8958999514579773,
      "test_loss": 0.363694429397583,
      "precision": 1.0,
      "recall": 0.0,
      "f1_score": 0.0,
      "update_norm": 0.0,
      "is_attacker": false,
      "eps_n": 4.8422348749350235
    },
    "149": {
      "accuracy": 0.8723999857902527,
      "test_loss": 0.43053850531578064,
      "precision": 0.0,
      "recall": 0.0,
      "f1_score": 0.0,
      "update_norm": 3.4979405403137207,
      "is_attacker": false,
      "krum_score": 160.39920043945312,
      "trust": 0.6984529495239258,
      "noise_norm": 136.5788116455078,
      "n_dp_norm": 136.5788116455078,
      "nsr": 2551.1317903290133,
      "sigma_dp": 0.8535304615955281,
      "sigma_n": 0.8535304615955281,
      "eps_n": 5.525929200066727
    },
    "150": {
      "accuracy": 0.8637999892234802,
      "test_loss": 0.45092207193374634,
      "precision": 1.0,
      "recall": 0.0,
      "f1_score": 0.0,
      "update_norm": 0.0,
      "is_attacker": false,
      "eps_n": 4.403488959982182
    },
    "151": {
      "accuracy": 0.8472999930381775,
      "test_loss": 0.5001979470252991,
      "precision": 1.0,
      "recall": 0.0,
      "f1_score": 0.0,
      "update_norm": 0.0,
      "is_attacker": false,
      "eps_n": 3.5849875222560543
    },
    "152": {
      "accuracy": 0.892799973487854,
      "test_loss": 0.37609946727752686,
      "precision": 1.0,
      "recall": 0.0,
      "f1_score": 0.0,
      "update_norm": 0.0,
      "is_attacker": false,
      "eps_n": 2.6778933337224764
    },
    "153": {
      "accuracy": 0.8888999819755554,
      "test_loss": 0.37881961464881897,
      "precision": 1.0,
      "recall": 0.0,
      "f1_score": 0.0,
      "update_norm": 0.0,
      "is_attacker": false,
      "eps_n": 3.9466563563146355
    },
    "154": {
      "accuracy": 0.871999979019165,
      "test_loss": 0.43271151185035706,
      "precision": 1.0,
      "recall": 0.0,
      "f1_score": 0.0,
      "update_norm": 0.0,
      "is_attacker": false,
      "eps_n": 5.439828352699041
    },
    "155": {
      "accuracy": 0.8933999538421631,
      "test_loss": 0.3711093068122864,
      "precision": 1.0,
      "recall": 0.0,
      "f1_score": 0.0,
      "update_norm": 0.0,
      "is_attacker": false,
      "eps_n": 2.5254248843654574
    },
    "156": {
      "accuracy": 0.8930999636650085,
      "test_loss": 0.36950868368148804,
      "precision": 1.0,
      "recall": 0.0,
      "f1_score": 0.0,
      "update_norm": 0.0,
      "is_attacker": false,
      "eps_n": 3.202162341253812
    },
    "157": {
      "accuracy": 0.897599995136261,
      "test_loss": 0.36664485931396484,
      "precision": 1.0,
      "recall": 0.0,
      "f1_score": 0.0,
      "update_norm": 0.0,
      "is_attacker": false,
      "eps_n": 4.331732333103867
    },
    "158": {
      "accuracy": 0.5234000086784363,
      "test_loss": 2.110285997390747,
      "precision": 0.0,
      "recall": 0.0,
      "f1_score": 0.0,
      "update_norm": 9.562850952148438,
      "is_attacker": false,
      "krum_score": 212.514404296875,
      "trust": 0.853552520275116,
      "noise_norm": 119.6912612915039,
      "n_dp_norm": 119.6912612915039,
      "nsr": 1048.124365990536,
      "sigma_dp": 0.7518190342843837,
      "sigma_n": 0.7518190342843837,
      "eps_n": 6.330962960607976
    },
    "159": {
      "accuracy": 0.8313999772071838,
      "test_loss": 0.5407337546348572,
      "precision": 1.0,
      "recall": 0.0,
      "f1_score": 0.0,
      "update_norm": 0.0,
      "is_attacker": false,
      "eps_n": 4.895889574708986
    },
    "160": {
      "accuracy": 0.8883999586105347,
      "test_loss": 0.38561540842056274,
      "precision": 1.0,
      "recall": 0.0,
      "f1_score": 0.0,
      "update_norm": 0.0,
      "is_attacker": false,
      "eps_n": 4.004840763771
    },
    "161": {
      "accuracy": 0.8867999911308289,
      "test_loss": 0.390562504529953,
      "precision": 1.0,
      "recall": 0.0,
      "f1_score": 0.0,
      "update_norm": 0.0,
      "is_attacker": false,
      "eps_n": 3.502057235165492
    },
    "162": {
      "accuracy": 0.8621999621391296,
      "test_loss": 0.4527439773082733,
      "precision": 1.0,
      "recall": 0.0,
      "f1_score": 0.0,
      "update_norm": 0.0,
      "is_attacker": false,
      "eps_n": 3.6703035230468712
    },
    "163": {
      "accuracy": 0.8678999543190002,
      "test_loss": 0.43124765157699585,
      "precision": 1.0,
      "recall": 0.0,
      "f1_score": 0.0,
      "update_norm": 0.0,
      "is_attacker": false,
      "eps_n": 5.433014937555648
    },
    "164": {
      "accuracy": 0.8902999758720398,
      "test_loss": 0.37754350900650024,
      "precision": 0.0,
      "recall": 0.0,
      "f1_score": 0.0,
      "update_norm": 1.0481340885162354,
      "is_attacker": false,
      "krum_score": 212.514404296875,
      "trust": 1.0,
      "noise_norm": 104.81330108642578,
      "n_dp_norm": 104.81330108642578,
      "nsr": 2214.1121303742534,
      "sigma_dp": 0.6557814881016614,
      "sigma_n": 0.6557814881016614,
      "eps_n": 6.920827264404566
    },
    "165": {
      "accuracy": 0.8575999736785889,
      "test_loss": 0.4750209450721741,
      "precision": 1.0,
      "recall": 0.0,
      "f1_score": 0.0,
      "update_norm": 0.0,
      "is_attacker": false,
      "eps_n": 3.5660579475930607
    },
    "166": {
      "accuracy": 0.8661999702453613,
      "test_loss": 0.43463388085365295,
      "precision": 1.0,
      "recall": 0.0,
      "f1_score": 0.0,
      "update_norm": 0.0,
      "is_attacker": false,
      "eps_n": 3.905848973403434
    },
    "167": {
      "accuracy": 0.8440999984741211,
      "test_loss": 0.49312981963157654,
      "precision": 0.0,
      "recall": 0.0,
      "f1_score": 0.0,
      "update_norm": 4.195717811584473,
      "is_attacker": false,
      "krum_score": 212.514404296875,
      "trust": 0.7677336931228638,
      "noise_norm": 128.84860229492188,
      "n_dp_norm": 128.84860229492188,
      "nsr": 2371.6850739442766,
      "sigma_dp": 0.808097432461427,
      "sigma_n": 0.808097432461427,
      "eps_n": 5.9026093828625665
    },
    "168": {
      "accuracy": 0.8914999961853027,
      "test_loss": 0.37078654766082764,
      "precision": 1.0,
      "recall": 0.0,
      "f1_score": 0.0,
      "update_norm": 0.0,
      "is_attacker": false,
      "eps_n": 0.0
    },
    "169": {
      "accuracy": 0.8898999691009521,
      "test_loss": 0.3742907643318176,
      "precision": 1.0,
      "recall": 0.0,
      "f1_score": 0.0,
      "update_norm": 0.0,
      "is_attacker": false,
      "eps_n": 0.0
    },
    "170": {
      "accuracy": 0.8410999774932861,
      "test_loss": 0.5243444442749023,
      "precision": 1.0,
      "recall": 0.0,
      "f1_score": 0.0,
      "update_norm": 0.0,
      "is_attacker": false,
      "eps_n": 3.5917101791701116
    },
    "171": {
      "accuracy": 0.8956999778747559,
      "test_loss": 0.36752310395240784,
      "precision": 1.0,
      "recall": 0.0,
      "f1_score": 0.0,
      "update_norm": 0.0,
      "is_attacker": false,
      "eps_n": 2.6195304049508525
    },
    "172": {
      "accuracy": 0.894599974155426,
      "test_loss": 0.3624722957611084,
      "precision": 1.0,
      "recall": 0.0,
      "f1_score": 0.0,
      "update_norm": 0.0,
      "is_attacker": false,
      "eps_n": 3.7063354355497413
    },
    "173": {
      "accuracy": 0.8860999941825867,
      "test_loss": 0.383505642414093,
      "precision": 1.0,
      "recall": 0.0,
      "f1_score": 0.0,
      "update_norm": 0.0,
      "is_attacker": false,
      "eps_n": 2.6008206763400725
    },
    "174": {
      "accuracy": 0.8919000029563904,
      "test_loss": 0.3737286925315857,
      "precision": 1.0,
      "recall": 0.0,
      "f1_score": 0.0,
      "update_norm": 0.0,
      "is_attacker": false,
      "eps_n": 2.444367403079083
    },
    "175": {
      "accuracy": 0.7658999562263489,
      "test_loss": 0.8407775163650513,
      "precision": 1.0,
      "recall": 0.0,
      "f1_score": 0.0,
      "update_norm": 0.0,
      "is_attacker": false,
      "eps_n": 4.646499514259445
    },
    "176": {
      "accuracy": 0.897599995136261,
      "test_loss": 0.36498725414276123,
      "precision": 1.0,
      "recall": 0.0,
      "f1_score": 0.0,
      "update_norm": 0.0,
      "is_attacker": false,
      "eps_n": 0.0
    },
    "177": {
      "accuracy": 0.8938999772071838,
      "test_loss": 0.37043023109436035,
      "precision": 1.0,
      "recall": 0.0,
      "f1_score": 0.0,
      "update_norm": 0.0,
      "is_attacker": false,
      "eps_n": 2.6778933337224764
    },
    "178": {
      "accuracy": 0.8348000049591064,
      "test_loss": 0.5391155481338501,
      "precision": 1.0,
      "recall": 0.0,
      "f1_score": 0.0,
      "update_norm": 0.0,
      "is_attacker": false,
      "eps_n": 5.252074867277392
    },
    "179": {
      "accuracy": 0.8966999650001526,
      "test_loss": 0.37059587240219116,
      "precision": 1.0,
      "recall": 0.0,
      "f1_score": 0.0,
      "update_norm": 0.0,
      "is_attacker": false,
      "eps_n": 4.8422348749350235
    },
    "180": {
      "accuracy": 0.8914999961853027,
      "test_loss": 0.3728265166282654,
      "precision": 1.0,
      "recall": 0.0,
      "f1_score": 0.0,
      "update_norm": 0.0,
      "is_attacker": false,
      "eps_n": 2.881675626726248
    },
    "181": {
      "accuracy": 0.8930000066757202,
      "test_loss": 0.3709544241428375,
      "precision": 1.0,
      "recall": 0.0,
      "f1_score": 0.0,
      "update_norm": 0.0,
      "is_attacker": false,
      "eps_n": 0.0
    },
    "182": {
      "accuracy": 0.8890999555587769,
      "test_loss": 0.3823161721229553,
      "precision": 1.0,
      "recall": 0.0,
      "f1_score": 0.0,
      "update_norm": 0.0,
      "is_attacker": false,
      "eps_n": 2.664503473129171
    },
    "183": {
      "accuracy": 0.8937000036239624,
      "test_loss": 0.3793337941169739,
      "precision": 1.0,
      "recall": 0.0,
      "f1_score": 0.0,
      "update_norm": 0.0,
      "is_attacker": false,
      "eps_n": 4.142372036780985
    },
    "184": {
      "accuracy": 0.8657999634742737,
      "test_loss": 0.45142483711242676,
      "precision": 1.0,
      "recall": 0.0,
      "f1_score": 0.0,
      "update_norm": 0.0,
      "is_attacker": false,
      "eps_n": 5.095452511795951
    },
    "185": {
      "accuracy": 0.8949999809265137,
      "test_loss": 0.3682516813278198,
      "precision": 1.0,
      "recall": 0.0,
      "f1_score": 0.0,
      "update_norm": 0.0,
      "is_attacker": false,
      "eps_n": 3.004859985004947
    },
    "186": {
      "accuracy": 0.8937000036239624,
      "test_loss": 0.3738749027252197,
      "precision": 1.0,
      "recall": 0.0,
      "f1_score": 0.0,
      "update_norm": 0.0,
      "is_attacker": false,
      "eps_n": 0.0
    },
    "187": {
      "accuracy": 0.8619999885559082,
      "test_loss": 0.4529793858528137,
      "precision": 1.0,
      "recall": 0.0,
      "f1_score": 0.0,
      "update_norm": 0.0,
      "is_attacker": false,
      "eps_n": 3.2573759192902036
    },
    "188": {
      "accuracy": 0.8953999876976013,
      "test_loss": 0.3633494973182678,
      "precision": 1.0,
      "recall": 0.0,
      "f1_score": 0.0,
      "update_norm": 0.0,
      "is_attacker": false,
      "eps_n": 2.5696906453486514
    },
    "189": {
      "accuracy": 0.81659996509552,
      "test_loss": 0.597361147403717,
      "precision": 1.0,
      "recall": 0.0,
      "f1_score": 0.0,
      "update_norm": 0.0,
      "is_attacker": false,
      "eps_n": 5.290858269828157
    },
    "190": {
      "accuracy": 0.8752999901771545,
      "test_loss": 0.41060417890548706,
      "precision": 1.0,
      "recall": 0.0,
      "f1_score": 0.0,
      "update_norm": 0.0,
      "is_attacker": false,
      "eps_n": 2.9897422706185846
    },
    "191": {
      "accuracy": 0.8499000072479248,
      "test_loss": 0.501649022102356,
      "precision": 1.0,
      "recall": 0.0,
      "f1_score": 0.0,
      "update_norm": 0.0,
      "is_attacker": false,
      "eps_n": 3.489314006963502
    },
    "192": {
      "accuracy": 0.8866999745368958,
      "test_loss": 0.38066816329956055,
      "precision": 1.0,
      "recall": 0.0,
      "f1_score": 0.0,
      "update_norm": 0.0,
      "is_attacker": false,
      "eps_n": 2.7088059203055814
    },
    "193": {
      "accuracy": 0.8917999863624573,
      "test_loss": 0.37608540058135986,
      "precision": 1.0,
      "recall": 0.0,
      "f1_score": 0.0,
      "update_norm": 0.0,
      "is_attacker": false,
      "eps_n": 3.229384770797028
    },
    "194": {
      "accuracy": 0.8384000062942505,
      "test_loss": 0.5072837471961975,
      "precision": 1.0,
      "recall": 0.0,
      "f1_score": 0.0,
      "update_norm": 0.0,
      "is_attacker": false,
      "eps_n": 3.9874737264282736
    },
    "195": {
      "accuracy": 0.8761999607086182,
      "test_loss": 0.41028574109077454,
      "precision": 0.0,
      "recall": 0.0,
      "f1_score": 0.0,
      "update_norm": 2.770512580871582,
      "is_attacker": false,
      "krum_score": 280.34112548828125,
      "trust": 0.7255790829658508,
      "noise_norm": 133.28977966308594,
      "n_dp_norm": 133.28977966308594,
      "nsr": 2746.998758639729,
      "sigma_dp": 0.8357416454405383,
      "sigma_n": 0.8357416454405383,
      "eps_n": 5.343649292384577
    },
    "196": {
      "accuracy": 0.8977999687194824,
      "test_loss": 0.3594263195991516,
      "precision": 1.0,
      "recall": 0.0,
      "f1_score": 0.0,
      "update_norm": 0.0,
      "is_attacker": false,
      "eps_n": 3.825013638073031
    },
    "197": {
      "accuracy": 0.892799973487854,
      "test_loss": 0.3757537603378296,
      "precision": 1.0,
      "recall": 0.0,
      "f1_score": 0.0,
      "update_norm": 0.0,
      "is_attacker": false,
      "eps_n": 6.345043387219871
    },
    "198": {
      "accuracy": 0.8930999636650085,
      "test_loss": 0.37164512276649475,
      "precision": 1.0,
      "recall": 0.0,
      "f1_score": 0.0,
      "update_norm": 0.0,
      "is_attacker": false,
      "eps_n": 5.9436989187151825
    },
    "199": {
      "accuracy": 0.8641999959945679,
      "test_loss": 0.44463667273521423,
      "precision": 0.0,
      "recall": 0.0,
      "f1_score": 0.0,
      "update_norm": 3.8271093368530273,
      "is_attacker": false,
      "krum_score": 282.5225830078125,
      "trust": 0.8021001815795898,
      "noise_norm": 125.0779037475586,
      "n_dp_norm": 125.0779037475586,
      "nsr": 2413.6442957634736,
      "sigma_dp": 0.7855605255204465,
      "sigma_n": 0.7855605255204465,
      "eps_n": 5.924567551706484
    },
    "200": {
      "accuracy": 0.8912000060081482,
      "test_loss": 0.3714795708656311,
      "precision": 1.0,
      "recall": 0.0,
      "f1_score": 0.0,
      "update_norm": 0.0,
      "is_attacker": false,
      "eps_n": 2.744531748257917
    },
    "201": {
      "accuracy": 0.8474999666213989,
      "test_loss": 0.49322521686553955,
      "precision": 1.0,
      "recall": 0.0,
      "f1_score": 0.0,
      "update_norm": 0.0,
      "is_attacker": false,
      "eps_n": 4.342833650018595
    },
    "202": {
      "accuracy": 0.8907999992370605,
      "test_loss": 0.37807202339172363,
      "precision": 1.0,
      "recall": 0.0,
      "f1_score": 0.0,
      "update_norm": 0.0,
      "is_attacker": false,
      "eps_n": 5.9436989187151825
    },
    "203": {
      "accuracy": 0.8233999609947205,
      "test_loss": 0.5843675136566162,
      "precision": 1.0,
      "recall": 0.0,
      "f1_score": 0.0,
      "update_norm": 0.0,
      "is_attacker": false,
      "eps_n": 4.714590815095843
    },
    "204": {
      "accuracy": 0.8473999500274658,
      "test_loss": 0.49354949593544006,
      "precision": 1.0,
      "recall": 0.0,
      "f1_score": 0.0,
      "update_norm": 0.0,
      "is_attacker": false,
      "eps_n": 4.424490276191301
    },
    "205": {
      "accuracy": 0.884399950504303,
      "test_loss": 0.3940107524394989,
      "precision": 1.0,
      "recall": 0.0,
      "f1_score": 0.0,
      "update_norm": 0.0,
      "is_attacker": false,
      "eps_n": 4.726487628566805
    },
    "206": {
      "accuracy": 0.887999951839447,
      "test_loss": 0.37475064396858215,
      "precision": 1.0,
      "recall": 0.0,
      "f1_score": 0.0,
      "update_norm": 0.0,
      "is_attacker": false,
      "eps_n": 3.283900602122412
    },
    "207": {
      "accuracy": 0.8912999629974365,
      "test_loss": 0.38064563274383545,
      "precision": 1.0,
      "recall": 0.0,
      "f1_score": 0.0,
      "update_norm": 0.0,
      "is_attacker": false,
      "eps_n": 3.9894460188169845
    },
    "208": {
      "accuracy": 0.8539999723434448,
      "test_loss": 0.47444388270378113,
      "precision": 0.0,
      "recall": 0.0,
      "f1_score": 0.0,
      "update_norm": 3.7570903301239014,
      "is_attacker": false,
      "krum_score": 282.5225830078125,
      "trust": 0.869930624961853,
      "noise_norm": 118.23258209228516,
      "n_dp_norm": 118.23258209228516,
      "nsr": 2358.630687819024,
      "sigma_dp": 0.7410785764206305,
      "sigma_n": 0.7410785764206305,
      "eps_n": 6.4194146033930375
    },
    "209": {
      "accuracy": 0.8944000005722046,
      "test_loss": 0.3679181933403015,
      "precision": 1.0,
      "recall": 0.0,
      "f1_score": 0.0,
      "update_norm": 0.0,
      "is_attacker": false,
      "eps_n": 6.345043387219871
    },
    "210": {
      "accuracy": 0.8848999738693237,
      "test_loss": 0.3911328613758087,
      "precision": 1.0,
      "recall": 0.0,
      "f1_score": 0.0,
      "update_norm": 0.0,
      "is_attacker": false,
      "eps_n": 4.840537653328616
    },
    "211": {
      "accuracy": 0.8940999507904053,
      "test_loss": 0.38047999143600464,
      "precision": 1.0,
      "recall": 0.0,
      "f1_score": 0.0,
      "update_norm": 0.0,
      "is_attacker": false,
      "eps_n": 4.142372036780985
    },
    "212": {
      "accuracy": 0.8924999833106995,
      "test_loss": 0.3750162422657013,
      "precision": 1.0,
      "recall": 0.0,
      "f1_score": 0.0,
      "update_norm": 0.0,
      "is_attacker": false,
      "eps_n": 2.5254248843654574
    },
    "213": {
      "accuracy": 0.8445000052452087,
      "test_loss": 0.5097706913948059,
      "precision": 0.0,
      "recall": 0.0,
      "f1_score": 0.0,
      "update_norm": 3.708083152770996,
      "is_attacker": false,
      "krum_score": 301.97265625,
      "trust": 0.7331392168998718,
      "noise_norm": 132.94117736816406,
      "n_dp_norm": 132.94117736816406,
      "nsr": 2320.0461047812,
      "sigma_dp": 0.8307838495590381,
      "sigma_n": 0.8307838495590381,
      "eps_n": 5.766526273793045
    },
    "214": {
      "accuracy": 0.8123999834060669,
      "test_loss": 0.5753320455551147,
      "precision": 1.0,
      "recall": 0.0,
      "f1_score": 0.0,
      "update_norm": 0.0,
      "is_attacker": false,
      "eps_n": 5.4043902284989835
    },
    "215": {
      "accuracy": 0.8828999996185303,
      "test_loss": 0.3910163640975952,
      "precision": 1.0,
      "recall": 0.0,
      "f1_score": 0.0,
      "update_norm": 0.0,
      "is_attacker": false,
      "eps_n": 2.838601540298663
    },
    "216": {
      "accuracy": 0.8211999535560608,
      "test_loss": 0.6193257570266724,
      "precision": 1.0,
      "recall": 0.0,
      "f1_score": 0.0,
      "update_norm": 0.0,
      "is_attacker": false,
      "eps_n": 3.814346060673093
    },
    "217": {
      "accuracy": 0.8938999772071838,
      "test_loss": 0.37661293148994446,
      "precision": 1.0,
      "recall": 0.0,
      "f1_score": 0.0,
      "update_norm": 0.0,
      "is_attacker": false,
      "eps_n": 2.744531748257917
    },
    "218": {
      "accuracy": 0.8960999846458435,
      "test_loss": 0.36940449476242065,
      "precision": 1.0,
      "recall": 0.0,
      "f1_score": 0.0,
      "update_norm": 0.0,
      "is_attacker": false,
      "eps_n": 6.345043387219871
    },
    "219": {
      "accuracy": 0.7566999793052673,
      "test_loss": 0.8399860262870789,
      "precision": 1.0,
      "recall": 0.0,
      "f1_score": 0.0,
      "update_norm": 0.0,
      "is_attacker": false,
      "eps_n": 4.761349285079626
    },
    "220": {
      "accuracy": 0.8889999985694885,
      "test_loss": 0.38504356145858765,
      "precision": 1.0,
      "recall": 0.0,
      "f1_score": 0.0,
      "update_norm": 0.0,
      "is_attacker": false,
      "eps_n": 4.43125975539763
    },
    "221": {
      "accuracy": 0.8932999968528748,
      "test_loss": 0.37517401576042175,
      "precision": 1.0,
      "recall": 0.0,
      "f1_score": 0.0,
      "update_norm": 0.0,
      "is_attacker": false,
      "eps_n": 2.7109457123184377
    },
    "222": {
      "accuracy": 0.8759999871253967,
      "test_loss": 0.4103143811225891,
      "precision": 1.0,
      "recall": 0.0,
      "f1_score": 0.0,
      "update_norm": 0.0,
      "is_attacker": false,
      "eps_n": 3.5040380596500196
    },
    "223": {
      "accuracy": 0.8310999870300293,
      "test_loss": 0.531830906867981,
      "precision": 1.0,
      "recall": 0.0,
      "f1_score": 0.0,
      "update_norm": 0.0,
      "is_attacker": false,
      "eps_n": 4.3023555266146944
    },
    "224": {
      "accuracy": 0.8297999501228333,
      "test_loss": 0.5449021458625793,
      "precision": 1.0,
      "recall": 0.0,
      "f1_score": 0.0,
      "update_norm": 0.0,
      "is_attacker": false,
      "eps_n": 4.895442176230342
    },
    "225": {
      "accuracy": 0.8527999520301819,
      "test_loss": 0.48486146330833435,
      "precision": 1.0,
      "recall": 0.0,
      "f1_score": 0.0,
      "update_norm": 0.0,
      "is_attacker": false,
      "eps_n": 4.965537775193408
    },
    "226": {
      "accuracy": 0.8941999673843384,
      "test_loss": 0.36737966537475586,
      "precision": 1.0,
      "recall": 0.0,
      "f1_score": 0.0,
      "update_norm": 0.0,
      "is_attacker": false,
      "eps_n": 4.8422348749350235
    },
    "227": {
      "accuracy": 0.8912999629974365,
      "test_loss": 0.36621972918510437,
      "precision": 1.0,
      "recall": 0.0,
      "f1_score": 0.0,
      "update_norm": 0.0,
      "is_attacker": false,
      "eps_n": 6.345043387219871
    },
    "228": {
      "accuracy": 0.8414999842643738,
      "test_loss": 0.5194185376167297,
      "precision": 1.0,
      "recall": 0.0,
      "f1_score": 0.0,
      "update_norm": 0.0,
      "is_attacker": false,
      "eps_n": 4.0368502290271016
    },
    "229": {
      "accuracy": 0.7410999536514282,
      "test_loss": 0.8209528923034668,
      "precision": 0.0,
      "recall": 0.0,
      "f1_score": 0.0,
      "update_norm": 6.665761947631836,
      "is_attacker": false,
      "krum_score": 343.9505310058594,
      "trust": 0.8452309370040894,
      "noise_norm": 120.67172241210938,
      "n_dp_norm": 120.67172241210938,
      "nsr": 2239.330603953898,
      "sigma_dp": 0.7572761745452194,
      "sigma_n": 0.7572761745452194,
      "eps_n": 6.053233220141617
    },
    "230": {
      "accuracy": 0.8758999705314636,
      "test_loss": 0.4116562306880951,
      "precision": 1.0,
      "recall": 0.0,
      "f1_score": 0.0,
      "update_norm": 0.0,
      "is_attacker": false,
      "eps_n": 4.025683350887168
    },
    "231": {
      "accuracy": 0.8619999885559082,
      "test_loss": 0.4534047842025757,
      "precision": 1.0,
      "recall": 0.0,
      "f1_score": 0.0,
      "update_norm": 0.0,
      "is_attacker": false,
      "eps_n": 4.801107080506264
    },
    "232": {
      "accuracy": 0.8800999522209167,
      "test_loss": 0.39912474155426025,
      "precision": 0.0,
      "recall": 0.0,
      "f1_score": 0.0,
      "update_norm": 2.357408285140991,
      "is_attacker": false,
      "krum_score": 343.9505310058594,
      "trust": 0.5516833066940308,
      "noise_norm": 152.05941772460938,
      "n_dp_norm": 152.05941772460938,
      "nsr": 3450.9647826662735,
      "sigma_dp": 0.949779276378666,
      "sigma_n": 0.949779276378666,
      "eps_n": 4.388754286089589
    },
    "233": {
      "accuracy": 0.8677999973297119,
      "test_loss": 0.4310592710971832,
      "precision": 1.0,
      "recall": 0.0,
      "f1_score": 0.0,
      "update_norm": 0.0,
      "is_attacker": false,
      "eps_n": 4.3425584892206155
    },
    "234": {
      "accuracy": 0.8889999985694885,
      "test_loss": 0.374902606010437,
      "precision": 1.0,
      "recall": 0.0,
      "f1_score": 0.0,
      "update_norm": 0.0,
      "is_attacker": false,
      "eps_n": 6.345043387219871
    },
    "235": {
      "accuracy": 0.8344999551773071,
      "test_loss": 0.5336712002754211,
      "precision": 1.0,
      "recall": 0.0,
      "f1_score": 0.0,
      "update_norm": 0.0,
      "is_attacker": false,
      "eps_n": 4.3813097126127465
    },
    "236": {
      "accuracy": 0.8932999968528748,
      "test_loss": 0.36811184883117676,
      "precision": 1.0,
      "recall": 0.0,
      "f1_score": 0.0,
      "update_norm": 0.0,
      "is_attacker": false,
      "eps_n": 2.6778933337224764
    },
    "237": {
      "accuracy": 0.8951999545097351,
      "test_loss": 0.36334702372550964,
      "precision": 1.0,
      "recall": 0.0,
      "f1_score": 0.0,
      "update_norm": 0.0,
      "is_attacker": false,
      "eps_n": 2.9072984788958705
    },
    "238": {
      "accuracy": 0.8904999494552612,
      "test_loss": 0.38044992089271545,
      "precision": 1.0,
      "recall": 0.0,
      "f1_score": 0.0,
      "update_norm": 0.0,
      "is_attacker": false,
      "eps_n": 3.464074705804752
    },
    "239": {
      "accuracy": 0.871399998664856,
      "test_loss": 0.423677921295166,
      "precision": 1.0,
      "recall": 0.0,
      "f1_score": 0.0,
      "update_norm": 0.0,
      "is_attacker": false,
      "eps_n": 3.731209711726552
    },
    "240": {
      "accuracy": 0.8389999866485596,
      "test_loss": 0.536156177520752,
      "precision": 1.0,
      "recall": 0.0,
      "f1_score": 0.0,
      "update_norm": 0.0,
      "is_attacker": false,
      "eps_n": 4.095360654630974
    },
    "241": {
      "accuracy": 0.8938999772071838,
      "test_loss": 0.36954498291015625,
      "precision": 1.0,
      "recall": 0.0,
      "f1_score": 0.0,
      "update_norm": 0.0,
      "is_attacker": false,
      "eps_n": 3.7053997925906774
    },
    "242": {
      "accuracy": 0.8906999826431274,
      "test_loss": 0.3726591169834137,
      "precision": 1.0,
      "recall": 0.0,
      "f1_score": 0.0,
      "update_norm": 0.0,
      "is_attacker": false,
      "eps_n": 0.0
    },
    "243": {
      "accuracy": 0.8723999857902527,
      "test_loss": 0.42232200503349304,
      "precision": 1.0,
      "recall": 0.0,
      "f1_score": 0.0,
      "update_norm": 0.0,
      "is_attacker": false,
      "eps_n": 3.4845234300075916
    },
    "244": {
      "accuracy": 0.873199999332428,
      "test_loss": 0.4199230372905731,
      "precision": 1.0,
      "recall": 0.0,
      "f1_score": 0.0,
      "update_norm": 0.0,
      "is_attacker": false,
      "eps_n": 3.8689624189021776
    },
    "245": {
      "accuracy": 0.839199960231781,
      "test_loss": 0.5024076104164124,
      "precision": 1.0,
      "recall": 0.0,
      "f1_score": 0.0,
      "update_norm": 0.0,
      "is_attacker": false,
      "eps_n": 3.910111067011825
    },
    "246": {
      "accuracy": 0.8736000061035156,
      "test_loss": 0.4260333776473999,
      "precision": 1.0,
      "recall": 0.0,
      "f1_score": 0.0,
      "update_norm": 0.0,
      "is_attacker": false,
      "eps_n": 4.573848297273777
    },
    "247": {
      "accuracy": 0.896399974822998,
      "test_loss": 0.361850768327713,
      "precision": 1.0,
      "recall": 0.0,
      "f1_score": 0.0,
      "update_norm": 0.0,
      "is_attacker": false,
      "eps_n": 0.0
    },
    "248": {
      "accuracy": 0.8696999549865723,
      "test_loss": 0.43189558386802673,
      "precision": 1.0,
      "recall": 0.0,
      "f1_score": 0.0,
      "update_norm": 0.0,
      "is_attacker": false,
      "eps_n": 3.5410308765304483
    },
    "249": {
      "accuracy": 0.875,
      "test_loss": 0.405714213848114,
      "precision": 1.0,
      "recall": 0.0,
      "f1_score": 0.0,
      "update_norm": 0.0,
      "is_attacker": false,
      "eps_n": 3.0566381826154085
    },
    "250": {
      "accuracy": 0.8826999664306641,
      "test_loss": 0.39204123616218567,
      "precision": 1.0,
      "recall": 0.0,
      "f1_score": 0.0,
      "update_norm": 0.0,
      "is_attacker": false,
      "eps_n": 2.8404491217042245
    },
    "251": {
      "accuracy": 0.8353999853134155,
      "test_loss": 0.5252845883369446,
      "precision": 1.0,
      "recall": 0.0,
      "f1_score": 0.0,
      "update_norm": 0.0,
      "is_attacker": false,
      "eps_n": 4.359341826397008
    },
    "252": {
      "accuracy": 0.8941999673843384,
      "test_loss": 0.3682739734649658,
      "precision": 1.0,
      "recall": 0.0,
      "f1_score": 0.0,
      "update_norm": 0.0,
      "is_attacker": false,
      "eps_n": 0.0
    },
    "253": {
      "accuracy": 0.8697999715805054,
      "test_loss": 0.41958457231521606,
      "precision": 1.0,
      "recall": 0.0,
      "f1_score": 0.0,
      "update_norm": 0.0,
      "is_attacker": false,
      "eps_n": 2.8538184025193316
    },
    "254": {
      "accuracy": 0.8964999914169312,
      "test_loss": 0.36482253670692444,
      "precision": 1.0,
      "recall": 0.0,
      "f1_score": 0.0,
      "update_norm": 0.0,
      "is_attacker": false,
      "eps_n": 2.5254248843654574
    },
    "255": {
      "accuracy": 0.8910999894142151,
      "test_loss": 0.3721434772014618,
      "precision": 1.0,
      "recall": 0.0,
      "f1_score": 0.0,
      "update_norm": 0.0,
      "is_attacker": false,
      "eps_n": 3.825013638073031
    },
    "256": {
      "accuracy": 0.8529999852180481,
      "test_loss": 0.4980604946613312,
      "precision": 0.0,
      "recall": 0.0,
      "f1_score": 0.0,
      "update_norm": 4.216111183166504,
      "is_attacker": false,
      "krum_score": 358.9456787109375,
      "trust": 0.7971068620681763,
      "noise_norm": 126.307861328125,
      "n_dp_norm": 126.307861328125,
      "nsr": 2557.9385211703193,
      "sigma_dp": 0.7888350520202084,
      "sigma_n": 0.7888350520202084,
      "eps_n": 5.812946519266503
    },
    "257": {
      "accuracy": 0.8962000012397766,
      "test_loss": 0.3600563704967499,
      "precision": 1.0,
      "recall": 0.0,
      "f1_score": 0.0,
      "update_norm": 0.0,
      "is_attacker": false,
      "eps_n": 2.6778933337224764
    },
    "258": {
      "accuracy": 0.8716999888420105,
      "test_loss": 0.42846882343292236,
      "precision": 1.0,
      "recall": 0.0,
      "f1_score": 0.0,
      "update_norm": 0.0,
      "is_attacker": false,
      "eps_n": 4.066509357612583
    },
    "259": {
      "accuracy": 0.8953999876976013,
      "test_loss": 0.361236035823822,
      "precision": 1.0,
      "recall": 0.0,
      "f1_score": 0.0,
      "update_norm": 0.0,
      "is_attacker": false,
      "eps_n": 0.0
    },
    "260": {
      "accuracy": 0.8773999810218811,
      "test_loss": 0.41050687432289124,
      "precision": 1.0,
      "recall": 0.0,
      "f1_score": 0.0,
      "update_norm": 0.0,
      "is_attacker": false,
      "eps_n": 5.074212719761965
    },
    "261": {
      "accuracy": 0.8928999900817871,
      "test_loss": 0.3733128309249878,
      "precision": 1.0,
      "recall": 0.0,
      "f1_score": 0.0,
      "update_norm": 0.0,
      "is_attacker": false,
      "eps_n": 2.8195636533734056
    },
    "262": {
      "accuracy": 0.8792999982833862,
      "test_loss": 0.4175684452056885,
      "precision": 1.0,
      "recall": 0.0,
      "f1_score": 0.0,
      "update_norm": 0.0,
      "is_attacker": false,
      "eps_n": 3.5912867217469557
    },
    "263": {
      "accuracy": 0.7501999735832214,
      "test_loss": 0.8142834305763245,
      "precision": 1.0,
      "recall": 0.0,
      "f1_score": 0.0,
      "update_norm": 0.0,
      "is_attacker": false,
      "eps_n": 5.053803992218248
    },
    "264": {
      "accuracy": 0.7942000031471252,
      "test_loss": 0.6969969868659973,
      "precision": 0.0,
      "recall": 0.0,
      "f1_score": 0.0,
      "update_norm": 6.887662887573242,
      "is_attacker": false,
      "krum_score": 358.9456787109375,
      "trust": 0.6898932456970215,
      "noise_norm": 137.16854858398438,
      "n_dp_norm": 137.16854858398438,
      "nsr": 2442.857922985002,
      "sigma_dp": 0.8591437569088449,
      "sigma_n": 0.8591437569088449,
      "eps_n": 5.174849150751299
    },
    "265": {
      "accuracy": 0.7793999910354614,
      "test_loss": 0.8004836440086365,
      "precision": 1.0,
      "recall": 0.0,
      "f1_score": 0.0,
      "update_norm": 0.0,
      "is_attacker": false,
      "eps_n": 5.563417755690442
    },
    "266": {
      "accuracy": 0.8906999826431274,
      "test_loss": 0.3792920410633087,
      "precision": 1.0,
      "recall": 0.0,
      "f1_score": 0.0,
      "update_norm": 0.0,
      "is_attacker": false,
      "eps_n": 5.203093445904507
    },
    "267": {
      "accuracy": 0.8700999617576599,
      "test_loss": 0.41920262575149536,
      "precision": 1.0,
      "recall": 0.0,
      "f1_score": 0.0,
      "update_norm": 0.0,
      "is_attacker": false,
      "eps_n": 3.617671629486246
    },
    "268": {
      "accuracy": 0.887499988079071,
      "test_loss": 0.37885919213294983,
      "precision": 1.0,
      "recall": 0.0,
      "f1_score": 0.0,
      "update_norm": 0.0,
      "is_attacker": false,
      "eps_n": 3.7943049670713913
    },
    "269": {
      "accuracy": 0.8804999589920044,
      "test_loss": 0.40612825751304626,
      "precision": 1.0,
      "recall": 0.0,
      "f1_score": 0.0,
      "update_norm": 0.0,
      "is_attacker": false,
      "eps_n": 3.581607817268587
    },
    "270": {
      "accuracy": 0.5406999588012695,
      "test_loss": 1.801811695098877,
      "precision": 0.0,
      "recall": 0.0,
      "f1_score": 0.0,
      "update_norm": 8.189857482910156,
      "is_attacker": false,
      "krum_score": 358.9456787109375,
      "trust": 0.8220990896224976,
      "noise_norm": 123.56546783447266,
      "n_dp_norm": 123.56546783447266,
      "nsr": 945.0793797761006,
      "sigma_dp": 0.7724456118436602,
      "sigma_n": 0.7724456118436602,
      "eps_n": 6.460130988226051
    },
    "271": {
      "accuracy": 0.8001999855041504,
      "test_loss": 0.736153244972229,
      "precision": 1.0,
      "recall": 0.0,
      "f1_score": 0.0,
      "update_norm": 0.0,
      "is_attacker": false,
      "eps_n": 4.719634358053268
    },
    "272": {
      "accuracy": 0.8434000015258789,
      "test_loss": 0.521320641040802,
      "precision": 1.0,
      "recall": 0.0,
      "f1_score": 0.0,
      "update_norm": 0.0,
      "is_attacker": false,
      "eps_n": 5.287544893634146
    },
    "273": {
      "accuracy": 0.8901000022888184,
      "test_loss": 0.37756651639938354,
      "precision": 1.0,
      "recall": 0.0,
      "f1_score": 0.0,
      "update_norm": 0.0,
      "is_attacker": false,
      "eps_n": 3.004859985004947
    },
    "274": {
      "accuracy": 0.8912999629974365,
      "test_loss": 0.3847939968109131,
      "precision": 0.0,
      "recall": 0.0,
      "f1_score": 0.0,
      "update_norm": 1.0423173904418945,
      "is_attacker": false,
      "krum_score": 350.1495361328125,
      "trust": 1.0,
      "noise_norm": 104.23141479492188,
      "n_dp_norm": 104.23141479492188,
      "nsr": 2096.581732034784,
      "sigma_dp": 0.6557814881016614,
      "sigma_n": 0.6557814881016614,
      "eps_n": 6.920827264404566
    },
    "275": {
      "accuracy": 0.8740999698638916,
      "test_loss": 0.4272489547729492,
      "precision": 1.0,
      "recall": 0.0,
      "f1_score": 0.0,
      "update_norm": 0.0,
      "is_attacker": false,
      "eps_n": 3.6862457109405407
    },
    "276": {
      "accuracy": 0.8565999865531921,
      "test_loss": 0.46619153022766113,
      "precision": 1.0,
      "recall": 0.0,
      "f1_score": 0.0,
      "update_norm": 0.0,
      "is_attacker": false,
      "eps_n": 3.433933723362866
    },
    "277": {
      "accuracy": 0.8842999935150146,
      "test_loss": 0.393718421459198,
      "precision": 1.0,
      "recall": 0.0,
      "f1_score": 0.0,
      "update_norm": 0.0,
      "is_attacker": false,
      "eps_n": 5.056584131105389
    },
    "278": {
      "accuracy": 0.8826999664306641,
      "test_loss": 0.39036422967910767,
      "precision": 1.0,
      "recall": 0.0,
      "f1_score": 0.0,
      "update_norm": 0.0,
      "is_attacker": false,
      "eps_n": 2.658847328940826
    },
    "279": {
      "accuracy": 0.8932999968528748,
      "test_loss": 0.3745456337928772,
      "precision": 1.0,
      "recall": 0.0,
      "f1_score": 0.0,
      "update_norm": 0.0,
      "is_attacker": false,
      "eps_n": 3.602137427473032
    },
    "280": {
      "accuracy": 0.8230999708175659,
      "test_loss": 0.5879889130592346,
      "precision": 1.0,
      "recall": 0.0,
      "f1_score": 0.0,
      "update_norm": 0.0,
      "is_attacker": false,
      "eps_n": 3.5765571295548106
    },
    "281": {
      "accuracy": 0.8962999582290649,
      "test_loss": 0.3612854480743408,
      "precision": 1.0,
      "recall": 0.0,
      "f1_score": 0.0,
      "update_norm": 0.0,
      "is_attacker": false,
      "eps_n": 0.0
    },
    "282": {
      "accuracy": 0.889799952507019,
      "test_loss": 0.37496259808540344,
      "precision": 1.0,
      "recall": 0.0,
      "f1_score": 0.0,
      "update_norm": 0.0,
      "is_attacker": false,
      "eps_n": 2.9944783511988637
    },
    "283": {
      "accuracy": 0.8907999992370605,
      "test_loss": 0.37263476848602295,
      "precision": 1.0,
      "recall": 0.0,
      "f1_score": 0.0,
      "update_norm": 0.0,
      "is_attacker": false,
      "eps_n": 0.0
    },
    "284": {
      "accuracy": 0.8877999782562256,
      "test_loss": 0.3897388279438019,
      "precision": 1.0,
      "recall": 0.0,
      "f1_score": 0.0,
      "update_norm": 0.0,
      "is_attacker": false,
      "eps_n": 3.571784741576551
    },
    "285": {
      "accuracy": 0.8931999802589417,
      "test_loss": 0.3699612319469452,
      "precision": 1.0,
      "recall": 0.0,
      "f1_score": 0.0,
      "update_norm": 0.0,
      "is_attacker": false,
      "eps_n": 3.112611879653195
    },
    "286": {
      "accuracy": 0.8925999999046326,
      "test_loss": 0.37291210889816284,
      "precision": 1.0,
      "recall": 0.0,
      "f1_score": 0.0,
      "update_norm": 0.0,
      "is_attacker": false,
      "eps_n": 3.6710004046220326
    },
    "287": {
      "accuracy": 0.8931999802589417,
      "test_loss": 0.3746967613697052,
      "precision": 1.0,
      "recall": 0.0,
      "f1_score": 0.0,
      "update_norm": 0.0,
      "is_attacker": false,
      "eps_n": 3.9761996984060364
    },
    "288": {
      "accuracy": 0.8258999586105347,
      "test_loss": 0.567480206489563,
      "precision": 0.0,
      "recall": 0.0,
      "f1_score": 0.0,
      "update_norm": 4.282177925109863,
      "is_attacker": false,
      "krum_score": 387.4482116699219,
      "trust": 0.8317073583602905,
      "noise_norm": 121.8734130859375,
      "n_dp_norm": 121.8734130859375,
      "nsr": 1706.9851418882006,
      "sigma_dp": 0.7661446870727097,
      "sigma_n": 0.7661446870727097,
      "eps_n": 7.020085620353753
    },
    "289": {
      "accuracy": 0.6735999584197998,
      "test_loss": 1.1964844465255737,
      "precision": 0.0,
      "recall": 0.0,
      "f1_score": 0.0,
      "update_norm": 7.776418209075928,
      "is_attacker": false,
      "krum_score": 372.52276611328125,
      "trust": 0.8477439880371094,
      "noise_norm": 120.25505828857422,
      "n_dp_norm": 120.25505828857422,
      "nsr": 1559.6383791362027,
      "sigma_dp": 0.7556281621991101,
      "sigma_n": 0.7556281621991101,
      "eps_n": 6.233340433103474
    },
    "290": {
      "accuracy": 0.871399998664856,
      "test_loss": 0.4258235692977905,
      "precision": 1.0,
      "recall": 0.0,
      "f1_score": 0.0,
      "update_norm": 0.0,
      "is_attacker": false,
      "eps_n": 3.7424399355110873
    },
    "291": {
      "accuracy": 0.873199999332428,
      "test_loss": 0.4245774447917938,
      "precision": 1.0,
      "recall": 0.0,
      "f1_score": 0.0,
      "update_norm": 0.0,
      "is_attacker": false,
      "eps_n": 4.628641029857307
    },
    "292": {
      "accuracy": 0.887999951839447,
      "test_loss": 0.39064323902130127,
      "precision": 1.0,
      "recall": 0.0,
      "f1_score": 0.0,
      "update_norm": 0.0,
      "is_attacker": false,
      "eps_n": 5.521182358185864
    },
    "293": {
      "accuracy": 0.8904999494552612,
      "test_loss": 0.3801669180393219,
      "precision": 1.0,
      "recall": 0.0,
      "f1_score": 0.0,
      "update_norm": 0.0,
      "is_attacker": false,
      "eps_n": 2.603397415216582
    },
    "294": {
      "accuracy": 0.8974999785423279,
      "test_loss": 0.36443814635276794,
      "precision": 1.0,
      "recall": 0.0,
      "f1_score": 0.0,
      "update_norm": 0.0,
      "is_attacker": false,
      "eps_n": 0.0
    },
    "295": {
      "accuracy": 0.7989999651908875,
      "test_loss": 0.7318845987319946,
      "precision": 1.0,
      "recall": 0.0,
      "f1_score": 0.0,
      "update_norm": 0.0,
      "is_attacker": false,
      "eps_n": 3.6971849715642437
    },
    "296": {
      "accuracy": 0.8468999862670898,
      "test_loss": 0.49901464581489563,
      "precision": 1.0,
      "recall": 0.0,
      "f1_score": 0.0,
      "update_norm": 0.0,
      "is_attacker": false,
      "eps_n": 3.585554714721932
    },
    "297": {
      "accuracy": 0.8876999616622925,
      "test_loss": 0.3803769052028656,
      "precision": 1.0,
      "recall": 0.0,
      "f1_score": 0.0,
      "update_norm": 0.0,
      "is_attacker": false,
      "eps_n": 0.0
    },
    "298": {
      "accuracy": 0.8574999570846558,
      "test_loss": 0.45885583758354187,
      "precision": 1.0,
      "recall": 0.0,
      "f1_score": 0.0,
      "update_norm": 0.0,
      "is_attacker": false,
      "eps_n": 3.502530571295897
    },
    "299": {
      "accuracy": 0.8789999485015869,
      "test_loss": 0.3976294696331024,
      "precision": 1.0,
      "recall": 0.0,
      "f1_score": 0.0,
      "update_norm": 0.0,
      "is_attacker": false,
      "eps_n": 3.5667079054071356
    }
  }
}